pylogbeat.py
pylogbeat-2.0.0.dist-info/LICENSE
pylogbeat-2.0.0.dist-info/METADATA
pylogbeat-2.0.0.dist-info/WHEEL
pylogbeat-2.0.0.dist-info/top_level.txt
pylogbeat-2.0.0.dist-info/RECORD
