Metadata-Version: 2.1
Name: pylogbeat
Version: 2.0.0
Summary: Simple, incomplete implementation of the Beats protocol used by Elastic Beats and Logstash.
Home-page: https://github.com/eht16/pylogbeat/
Author: Enrico Tröger
Author-email: enrico.troeger@uvena.de
License: Apache License 2.0
Project-URL: Travis CI, https://travis-ci.org/eht16/pylogbeat/
Project-URL: Source code, https://github.com/eht16/pylogbeat/
Keywords: logging logstash beats
Platform: UNKNOWN
Classifier: Development Status :: 5 - Production/Stable
Classifier: Intended Audience :: Developers
Classifier: License :: OSI Approved :: Apache Software License
Classifier: Operating System :: OS Independent
Classifier: Programming Language :: Python
Classifier: Programming Language :: Python :: 3
Classifier: Topic :: Internet :: WWW/HTTP
Classifier: Topic :: Software Development :: Libraries :: Python Modules
Classifier: Topic :: System :: Logging
Requires-Python: >3.6
